streamlit_flexselect/__init__.py
streamlit_flexselect/example.py
streamlit_flexselect/streamlit_callback.py
streamlit_flexselect/frontend/build/asset-manifest.json
streamlit_flexselect/frontend/build/bootstrap.min.css
streamlit_flexselect/frontend/build/index.html
streamlit_flexselect/frontend/build/static/js/main.9d197e66.js
streamlit_flexselect/frontend/build/static/js/main.9d197e66.js.LICENSE.txt
streamlit_flexselect/frontend/build/static/js/main.9d197e66.js.map
streamlit_flexselect/frontend/build/static/js/main.e422096e.js
streamlit_flexselect/frontend/build/static/js/main.e422096e.js.LICENSE.txt
streamlit_flexselect/frontend/build/static/js/main.e422096e.js.map
streamlit_flexselect-0.0.6.dist-info/LICENSE
streamlit_flexselect-0.0.6.dist-info/METADATA
streamlit_flexselect-0.0.6.dist-info/WHEEL
streamlit_flexselect-0.0.6.dist-info/top_level.txt
streamlit_flexselect-0.0.6.dist-info/RECORD
